mycreds_package/MyCreds.py
mycreds_package/__init__.py
mycreds_package/certMaker/__init__.py
mycreds_package/certMaker/certMaker.py
mycreds_package/certMaker/csvReader.py
mycreds_package/certMaker/drawCert.py
mycreds_package/certMaker/getCertType.py
mycreds_package/certMaker/regCustomFonts.py
mycreds_package/certMaker/splitLongString.py
mycreds_package/certMaker/fonts/BureauGrotCondensed-Bold.ttf
mycreds_package/certMaker/fonts/LeMondeLivreStd-Demi.ttf
mycreds_package/certMaker/fonts/Typ1451Std-Regular.ttf
mycreds_package/certMaker/fonts/__init__.py
mycreds_package/certMaker/templates/__init__.py
mycreds_package/certMaker/templates/bronzeCertTemp.jpg
mycreds_package/certMaker/templates/goldCertTemp.jpg
mycreds_package/certMaker/templates/silverCertTemp.jpg
mycreds_package/csvMaker/__init__.py
mycreds_package/csvMaker/csvLists.py
mycreds_package/csvMaker/csvMaker.py
mycreds_package/csvMaker/dateFormatter.py
mycreds_package/csvMaker/nameFormatter.py
mycreds_package/scraper/__init__.py
mycreds_package/scraper/dataCollector.py
mycreds_package/scraper/getCourseSec.py
mycreds_package/scraper/getCredentials.py
mycreds_package/scraper/navClassList.py
mycreds_package/scraper/navGradingSheet.py
mycreds_package/scraper/scraper.py
mycreds_package/scraper/ssoLogin.py
mycreds_package-1.0.dist-info/LICENSE.txt
mycreds_package-1.0.dist-info/METADATA
mycreds_package-1.0.dist-info/WHEEL
mycreds_package-1.0.dist-info/entry_points.txt
mycreds_package-1.0.dist-info/top_level.txt
mycreds_package-1.0.dist-info/RECORD
