Metadata-Version: 2.1
Name: mycreds_package
Version: 1.0
Summary: MyCreds Project Package
Author-email: David Wong <d78wong@uwaterloo.ca>
Project-URL: Homepage, https://github.com/wongd1532/MyCreds/
Requires-Python: >=3.12
License-File: LICENSE.txt
Requires-Dist: reportlab
Requires-Dist: selenium
